rentdown/__init__.py
rentdown/countdown.py
rentdown-0.3.0.dist-info/METADATA
rentdown-0.3.0.dist-info/WHEEL
rentdown-0.3.0.dist-info/top_level.txt
rentdown-0.3.0.dist-info/RECORD
