Metadata-Version: 2.1
Name: rentdown
Version: 0.3.0
Summary: A Python library for managing rent expiration countdowns
Home-page: http://x23129522-barterproj-env.eba-mppyp5zh.eu-west-1.elasticbeanstalk.com/
Author: Ezekiel Ayanda
Author-email: ayandaezekiel@gmail.com
License: MIT
Classifier: Programming Language :: Python :: 3
Classifier: License :: OSI Approved :: MIT License
Classifier: Operating System :: OS Independent
Requires-Python: >=3.6
